cytoplots/__init__.py
cytoplots/general.py
cytoplots/hist.py
cytoplots/transforms/__init__.py
cytoplots/transforms/asinh_transform.py
cytoplots/transforms/hlog_transform.py
cytoplots/transforms/logicle_transform.py
cytoplots-0.1.12.dist-info/LICENSE
cytoplots-0.1.12.dist-info/WHEEL
cytoplots-0.1.12.dist-info/METADATA
cytoplots-0.1.12.dist-info/RECORD
